vector_sdk/__init__.py
vector_sdk/exceptions.py
vector_sdk/factory.py
vector_sdk/main.py
vector_sdk/adapters/__init__.py
vector_sdk/adapters/abc_adapter.py
vector_sdk/adapters/base_adapter.py
vector_sdk/adapters/milvus_adapter.py
vector_sdk/adapters/pinecone_adapter.py
vector_sdk/adapters/qdrant_adapter.py
vector_sdk/adapters/weaviate_adapter.py
vector_sdk/core/vector_db_interface.py
vector_sdk/export_vdf/export_abc.py
vector_sdk/export_vdf/export_vdf.py
vector_sdk/import_vdf/import_abc.py
vector_sdk/import_vdf/import_vdf.py
vector_sdk/utils/telemetry.py
vector_sdk-0.1.1.dist-info/METADATA
vector_sdk-0.1.1.dist-info/WHEEL
vector_sdk-0.1.1.dist-info/entry_points.txt
vector_sdk-0.1.1.dist-info/licenses/LICENSE
vector_sdk-0.1.1.dist-info/RECORD
