Metadata-Version: 2.3
Name: vector-sdk
Version: 0.1.1
Summary: Universal SDK for Vector DBs
Project-URL: Homepage, https://github.com/dhruv-anand-aintech/vector-sdk.git
Project-URL: Bug Tracker, https://github.com/dhruv-anand-aintech/vector-sdk/issues
Author-email: Dhruv Anand <dhruv.anand@ainorthstartech.com>, Hadi Khan <hadikhan.techx@gmail.com>
Classifier: Development Status :: 3 - Alpha
Classifier: Intended Audience :: Developers
Classifier: License :: OSI Approved :: MIT License
Classifier: Operating System :: OS Independent
Classifier: Programming Language :: Python :: 3.10
Classifier: Programming Language :: Python :: 3.11
Classifier: Programming Language :: Python :: 3.12
Requires-Python: >=3.10
Provides-Extra: dev
Requires-Dist: build; extra == 'dev'
Requires-Dist: pre-commit; extra == 'dev'
Requires-Dist: pytest-cov>=2.0; extra == 'dev'
Requires-Dist: pytest>=6.0; extra == 'dev'
Requires-Dist: qdrant-client[fastembed]; extra == 'dev'
Requires-Dist: ruff>=0.1.6; extra == 'dev'
Requires-Dist: uv>=0.1.0; extra == 'dev'
